CHANGES.txt
LICENSE.txt
MANIFEST.in
README.rst
setup.py
version.py
bin/entropy
bin/entropy.cfg
entropyrate/__init__.py
entropyrate/entropyrate.py
entropyrate.egg-info/PKG-INFO
entropyrate.egg-info/SOURCES.txt
entropyrate.egg-info/dependency_links.txt
entropyrate.egg-info/requires.txt
entropyrate.egg-info/top_level.txt
entropyrate/bin/entropy
entropyrate/bin/entropy.cfg
example/script.py
example/test.dat