Metadata-Version: 2.1
Name: entropyrate
Version: 0.0.13
Summary: Python wrappers for computing entropy rate of ergodic stationary finite valued processes
Home-page: https://github.com/zeroknowledgediscovery/
Author: zed.uchicago.edu
Author-email: ishanu@uchicago.edu
License: LICENSE.txt
Download-URL: https://github.com/zeroknowledgediscovery/entropyrate/archive/0.0.13.tar.gz
Keywords: entropy
Platform: UNKNOWN
Classifier: Development Status :: 4 - Beta
Classifier: Intended Audience :: Developers
Classifier: Intended Audience :: Science/Research
Classifier: Topic :: Scientific/Engineering :: Information Analysis
Classifier: Topic :: Software Development :: Libraries
Classifier: License :: OSI Approved :: MIT License
Classifier: Programming Language :: Python :: 2.7
Requires-Python: ==2.7.*
